windmill_client/__init__.py
windmill_client/client.py
windmill_client-0.7.1.dist-info/LICENSE
windmill_client-0.7.1.dist-info/WHEEL
windmill_client-0.7.1.dist-info/METADATA
windmill_client-0.7.1.dist-info/RECORD
