Metadata-Version: 2.1
Name: windmill_client
Version: 0.7.1
Summary: A client for the Windmill API
Author-email: Stephan Fitzpatrick <knowsuchagency@gmail.com>
Classifier: License :: OSI Approved :: MIT License
Requires-Dist: httpx~=0.25
